synth_mind/__init__.py
synth_mind/supervised/__init__.py
synth_mind/supervised/_action.py
synth_mind/supervised/_action_impl.py
synth_mind/supervised/_dataset.py
synth_mind/supervised/_general_action.py
synth_mind/supervised/_manager.py
synth_mind/supervised/data.py
synth_mind/supervised/handlers.py
synth_mind-0.1.4.dist-info/METADATA
synth_mind-0.1.4.dist-info/WHEEL
synth_mind-0.1.4.dist-info/licenses/LICENSE
synth_mind-0.1.4.dist-info/RECORD
