Metadata-Version: 2.3
Name: synth_mind
Version: 0.1.4
Summary: SynthMind: A Comprehensive Machine Learning Library
Project-URL: Homepage, https://github.com/lucasbasquerotto/synth-mind
Project-URL: Issues, https://github.com/lucasbasquerotto/synth-mind/issues
Author-email: Lucas Basquerotto <lucasbasquerotto@gmail.com>
License-File: LICENSE
Classifier: License :: OSI Approved :: MIT License
Classifier: Operating System :: OS Independent
Classifier: Programming Language :: Python :: 3
Requires-Python: >=3.8
